LICENSE
MANIFEST.in
README.md
pyproject.toml
setup.py
scheduletask/__init__.py
scheduletask/__main__.py
scheduletask/scheduletask.py
scheduletask.egg-info/PKG-INFO
scheduletask.egg-info/SOURCES.txt
scheduletask.egg-info/dependency_links.txt
scheduletask.egg-info/entry_points.txt
scheduletask.egg-info/top_level.txt