Metadata-Version: 2.1
Name: scheduletask
Version: 2.0.1
Summary: Create google calendar events from the command line
Home-page: https://github.com/shinwaffle/scheduletask
Author: Shinwaffle
Author-email: shinwaffle@gmail.com
License: UNKNOWN
Platform: UNKNOWN
Classifier: Programming Language :: Python :: 3
Classifier: License :: OSI Approved :: MIT License
Classifier: Operating System :: OS Independent
Requires-Python: >=3.6
License-File: LICENSE
